shelvery/__init__.py
shelvery/aws_helper.py
shelvery/backup_resource.py
shelvery/documentdb_backup.py
shelvery/ebs_backup.py
shelvery/ec2_backup.py
shelvery/ec2ami_backup.py
shelvery/engine.py
shelvery/entity_resource.py
shelvery/factory.py
shelvery/notifications.py
shelvery/queue.py
shelvery/rds_backup.py
shelvery/rds_cluster_backup.py
shelvery/redshift_backup.py
shelvery/runtime_config.py
shelvery/shelvery_invoker.py
shelvery_cli/__init__.py
shelvery_cli/__main__.py
shelvery_cli/shelver_cli_main.py
shelvery_lambda/__init__.py
shelvery_lambda/lambda_handler.py
shelvery-0.9.11.dist-info/LICENSE.txt
shelvery-0.9.11.dist-info/METADATA
shelvery-0.9.11.dist-info/WHEEL
shelvery-0.9.11.dist-info/entry_points.txt
shelvery-0.9.11.dist-info/top_level.txt
shelvery-0.9.11.dist-info/RECORD
