Metadata-Version: 2.1
Name: shelvery
Version: 0.9.11
Summary: Backup manager for AWS EBS and AWS RDS services
Home-page: http://github.com/base2Services/shelvery-aws-backups
Author: Base2Services R&D
Author-email: itsupport@base2services.com
Keywords: aws backup lambda ebs rds ami
Classifier: Development Status :: 3 - Alpha
Classifier: Programming Language :: Python :: 3.6
Classifier: Intended Audience :: System Administrators
Classifier: Intended Audience :: Information Technology
Classifier: License :: OSI Approved :: MIT License
Classifier: Topic :: System :: Archiving :: Backup
Requires-Python: >=3.6
License-File: LICENSE.txt
Requires-Dist: boto3
Requires-Dist: python-dateutil
Requires-Dist: pyyaml
